travel_purpose_and_city_tags/__init__.py
travel_purpose_and_city_tags/core.py
travel_purpose_and_city_tags-0.1.0.dist-info/METADATA
travel_purpose_and_city_tags-0.1.0.dist-info/WHEEL
travel_purpose_and_city_tags-0.1.0.dist-info/top_level.txt
travel_purpose_and_city_tags-0.1.0.dist-info/RECORD
