Metadata-Version: 2.4
Name: travel-purpose-and-city-tags
Version: 0.1.0
Summary: Travel purpose tagging library for city-specific travel behavior classification.
Author-email: Teyfik Öz <teyfik@example.com>
License: MIT
Requires-Python: >=3.8
